structure/__init__.py
structure/main.py
create_struc-1.0.2.dist-info/LICENSE
create_struc-1.0.2.dist-info/METADATA
create_struc-1.0.2.dist-info/WHEEL
create_struc-1.0.2.dist-info/entry_points.txt
create_struc-1.0.2.dist-info/top_level.txt
create_struc-1.0.2.dist-info/RECORD
