Metadata-Version: 2.1
Name: create_struc
Version: 1.0.2
Summary: A simple Create Structure tool.
Home-page: https://github.com/hemaabokila/create_structure
Author: Ibrahem abo kila
Author-email: ibrahemabokila@gmail.com
Classifier: Programming Language :: Python :: 3
Classifier: License :: OSI Approved :: MIT License
Classifier: Operating System :: OS Independent
Requires-Python: >=3.6
License-File: LICENSE
